proxy_pool/__init__.py
proxy_pool/data5u_proxy.py
proxy_pool/ip_pool.py
proxy_pool/xun_proxy.py
ggq_proxy_pool-0.2.1.dist-info/LICENSE
ggq_proxy_pool-0.2.1.dist-info/METADATA
ggq_proxy_pool-0.2.1.dist-info/WHEEL
ggq_proxy_pool-0.2.1.dist-info/top_level.txt
ggq_proxy_pool-0.2.1.dist-info/RECORD
