Metadata-Version: 2.1
Name: ggq-proxy-pool
Version: 0.2.1
Summary: 爬虫代理IP池
Home-page: https://github.com/ggqshr/proxy_pool
Author: ggq
Author-email: 942490944@qq.com
License: UNKNOWN
Platform: UNKNOWN
Classifier: Programming Language :: Python :: 3
Classifier: License :: OSI Approved :: MIT License
Classifier: Operating System :: OS Independent
Requires-Dist: requests (==2.22.0)
